igwn_ligolw-2.1.0.dist-info/RECORD
igwn_ligolw-2.1.0.dist-info/WHEEL
igwn_ligolw-2.1.0.dist-info/top_level.txt
igwn_ligolw-2.1.0.dist-info/METADATA
igwn_ligolw-2.1.0.dist-info/licenses/LICENSE
igwn_ligolw-2.1.0.data/scripts/igwn_ligolw_sqlite
igwn_ligolw-2.1.0.data/scripts/igwn_ligolw_no_ilwdchar
igwn_ligolw-2.1.0.data/scripts/igwn_ligolw_add
igwn_ligolw-2.1.0.data/scripts/igwn_ligolw_segments
igwn_ligolw-2.1.0.data/scripts/igwn_ligolw_run_sqlite
igwn_ligolw-2.1.0.data/scripts/igwn_ligolw_print
igwn_ligolw-2.1.0.data/scripts/igwn_ligolw_cut
igwn_ligolw/tokenizer.cpython-311-darwin.so
igwn_ligolw/_version.py
igwn_ligolw/ligolw.py
igwn_ligolw/lsctables.py
igwn_ligolw/tokenizer.RowDumper.c
igwn_ligolw/__init__.py
igwn_ligolw/tokenizer.h
igwn_ligolw/param.py
igwn_ligolw/types.py
igwn_ligolw/tokenizer.RowBuilder.c
igwn_ligolw/tokenizer.Tokenizer.c
igwn_ligolw/dbtables.py
igwn_ligolw/table.py
igwn_ligolw/array.py
igwn_ligolw/tokenizer.c
igwn_ligolw/utils/ligolw_add.py
igwn_ligolw/utils/search_summary.py
igwn_ligolw/utils/ilwd.py
igwn_ligolw/utils/segments.py
igwn_ligolw/utils/__init__.py
igwn_ligolw/utils/ligolw_sqlite.py
igwn_ligolw/utils/coincs.py
igwn_ligolw/utils/process.py
igwn_ligolw/utils/time_slide.py
